nbimports/__init__.py
nbimports/__main__.py
nbimports/cli.py
nbimports/constants.py
nbimports/templates/__init__.py
nbimports/templates/config.template
nbimports/templates/jinja.py
nbimports/templates/notebook.template
nbimports-0.0.3.dist-info/LICENSE
nbimports-0.0.3.dist-info/METADATA
nbimports-0.0.3.dist-info/WHEEL
nbimports-0.0.3.dist-info/entry_points.txt
nbimports-0.0.3.dist-info/top_level.txt
nbimports-0.0.3.dist-info/RECORD
