Metadata-Version: 2.1
Name: nbimports
Version: 0.0.3
Summary: A CLI tool for managing local module imports in jupyter notebooks
Author-email: Shiladitya Bose <shiladitya.31.z@gmail.com>
License: Copyright 2023 Shiladitya Bose
Project-URL: Homepage, https://github.com/s-bose/nbimports
Keywords: nbimports,nbimport,notebook
Classifier: License :: OSI Approved :: MIT License
Classifier: Programming Language :: Python
Classifier: Programming Language :: Python :: 3
Requires-Python: >=3.10
License-File: LICENSE
Requires-Dist: Jinja2 (>=3.1.2)
Requires-Dist: questionary (>=1.10.0)
Requires-Dist: rich (>=13.3.1)
Requires-Dist: typer (>=0.7.0)
Provides-Extra: dev
Requires-Dist: black ; extra == 'dev'
Requires-Dist: bumpver ; extra == 'dev'
Requires-Dist: isort ; extra == 'dev'
Requires-Dist: pip-tools ; extra == 'dev'
Requires-Dist: pytest ; extra == 'dev'
